{
  "subject": "English",
  "subject_code": "101",
  "year": "2025",
  "paper": "2025-english-09-question-paper",
  "total_questions": 16,
  "chapters": [
    {
      "chapter_id": "1012025uestionpaper",
      "chapter": "English CUET 2025 Past Year Paper - 2025-english-09-question-paper",
      "questions": [
        {
          "id": "101-2025-2025-english-09-question-paper-Q01",
          "type": "mcq",
          "level": "L2",
          "difficulty": "medium",
          "question": "Rearrange the following parts to form a meaningful sentence: P. and responded with immense courage Q. the citizens faced the calamity R. despite the lack of resources S. during the natural disaster",
          "options": [
            "Q-S-P-R",
            "Q-R-P-S",
            "R-Q-S-P",
            "Q-S-R-P"
          ],
          "correct": 3,
          "explanation": "The meaningful order is Q-S-R-P: the citizens faced the calamity during the natural disaster despite the lack of resources and responded with immense courage.",
          "source": "Individual PDF extraction: 2025-english-09-question-paper.pdf"
        },
        {
          "id": "101-2025-2025-english-09-question-paper-Q02",
          "type": "mcq",
          "level": "L2",
          "difficulty": "medium",
          "question": "Rearrange the following parts to form a meaningful sentence: P. without understanding the long-term consequences Q. on environmental sustainability R. many industries exploit natural resources S. which has a severe impact",
          "options": [
            "R-P-S-Q",
            "R-Q-S-P",
            "P-R-S-Q",
            "R-P-Q-S"
          ],
          "correct": 0,
          "explanation": "The meaningful order is R-P-S-Q: many industries exploit natural resources without understanding the long-term consequences, which has a severe impact on environmental sustainability.",
          "source": "Individual PDF extraction: 2025-english-09-question-paper.pdf"
        },
        {
          "id": "101-2025-2025-english-09-question-paper-Q03",
          "type": "mcq",
          "level": "L2",
          "difficulty": "medium",
          "question": "Rearrange the following parts to form a meaningful sentence: P. unless innovative policies are introduced Q. to reduce the digital divide R. access to technology will remain unequal S. in developing countries",
          "options": [
            "R-S-P-Q",
            "S-R-P-Q",
            "R-P-S-Q",
            "R-S-Q-P"
          ],
          "correct": 0,
          "explanation": "The meaningful order is R-S-P-Q: access to technology will remain unequal in developing countries unless innovative policies are introduced to reduce the digital divide.",
          "source": "Individual PDF extraction: 2025-english-09-question-paper.pdf"
        },
        {
          "id": "101-2025-2025-english-09-question-paper-Q04",
          "type": "mcq",
          "level": "L2",
          "difficulty": "medium",
          "question": "Despite his injuries, the player continued to play with great .",
          "options": [
            "agony",
            "hesitation",
            "valor",
            "ignorance"
          ],
          "correct": 2,
          "explanation": "Valor means great courage, which fits a player continuing despite injuries.",
          "source": "Individual PDF extraction: 2025-english-09-question-paper.pdf"
        },
        {
          "id": "101-2025-2025-english-09-question-paper-Q05",
          "type": "mcq",
          "level": "L2",
          "difficulty": "medium",
          "question": "The manager was impressed by her ability to handle the crisis with such .",
          "options": [
            "panic",
            "composure",
            "reluctance",
            "anxiety"
          ],
          "correct": 1,
          "explanation": "Composure means calmness and self-control, which fits handling a crisis well.",
          "source": "Individual PDF extraction: 2025-english-09-question-paper.pdf"
        },
        {
          "id": "101-2025-2025-english-09-question-paper-Q06",
          "type": "mcq",
          "level": "L2",
          "difficulty": "medium",
          "question": "The CEO’s sudden resignationthrew the board into a tailspin . What does the idiom ”threw into a tailspin” mean?",
          "options": [
            "Made them very successful",
            "Caused extreme confusion and panic",
            "Motivated them to act",
            "Made them feel hopeful"
          ],
          "correct": 1,
          "explanation": "To throw someone into a tailspin means to cause extreme confusion, panic, or loss of control.",
          "source": "Individual PDF extraction: 2025-english-09-question-paper.pdf"
        },
        {
          "id": "101-2025-2025-english-09-question-paper-Q07",
          "type": "mcq",
          "level": "L2",
          "difficulty": "medium",
          "question": "The politician’s vague answers clearly showed he was justbeating around the bush . What does ”beating around the bush” imply?",
          "options": [
            "Giving detailed explanations",
            "Avoiding the main point",
            "Being brutally honest",
            "Talking nonsense"
          ],
          "correct": 1,
          "explanation": "Beating around the bush means avoiding the main point instead of speaking directly.",
          "source": "Individual PDF extraction: 2025-english-09-question-paper.pdf"
        },
        {
          "id": "101-2025-2025-english-09-question-paper-Q08",
          "type": "mcq",
          "level": "L2",
          "difficulty": "medium",
          "question": "Find the errors in the underlined part: The committee has met yesterday to discuss the budget proposal.",
          "options": [
            "has met",
            "yesterday",
            "to discuss",
            "No error"
          ],
          "correct": 0,
          "explanation": "With the finished-time adverb yesterday, the simple past is needed: the committee met yesterday. The erroneous part is has met.",
          "source": "Individual PDF extraction: 2025-english-09-question-paper.pdf"
        },
        {
          "id": "101-2025-2025-english-09-question-paper-Q09",
          "type": "mcq",
          "level": "L2",
          "difficulty": "medium",
          "question": "Find the errors in the underlined part: Each of the students have submitted their assignments on time.",
          "options": [
            "Each of the students",
            "have submitted",
            "their assignments",
            "No error"
          ],
          "correct": 1,
          "explanation": "Each is singular, so the verb should be has submitted. The erroneous part is have submitted.",
          "source": "Individual PDF extraction: 2025-english-09-question-paper.pdf"
        },
        {
          "id": "101-2025-2025-english-09-question-paper-Q10",
          "type": "mcq",
          "level": "L2",
          "difficulty": "medium",
          "question": "Find the errors in underlined part: She is one of those rare individuals who goes out of her way to help others.",
          "options": [
            "one of those",
            "rare individuals",
            "who goes",
            "No error"
          ],
          "correct": 2,
          "explanation": "The relative pronoun who refers to plural individuals, so the verb should be go, not goes.",
          "source": "Individual PDF extraction: 2025-english-09-question-paper.pdf"
        },
        {
          "id": "101-2025-2025-english-09-question-paper-Q11",
          "type": "mcq",
          "level": "L2",
          "difficulty": "medium",
          "question": "Despite facing criticism, she decided to take the bull by the horns and defend her decision. What does the idiom “take the bull by the horns” mean?",
          "options": [
            "Avoid the responsibility",
            "Postpone the decision",
            "Face a difficult situation bravely",
            "Ignore the consequences"
          ],
          "correct": 2,
          "explanation": "To take the bull by the horns means to face a difficult situation directly and bravely.",
          "source": "Individual PDF extraction: 2025-english-09-question-paper.pdf"
        },
        {
          "id": "101-2025-2025-english-09-question-paper-Q12",
          "type": "mcq",
          "level": "L2",
          "difficulty": "medium",
          "question": "The novel was so engaging that I was completely in the story. Choose the word that best replaces the phrase “completely in the story”.",
          "options": [
            "isolated",
            "immersed",
            "abandoned",
            "confused"
          ],
          "correct": 1,
          "explanation": "Immersed means deeply absorbed or completely involved in something, such as a story.",
          "source": "Individual PDF extraction: 2025-english-09-question-paper.pdf"
        },
        {
          "id": "101-2025-2025-english-09-question-paper-Q13",
          "type": "mcq",
          "level": "L2",
          "difficulty": "medium",
          "question": "Choose the word that is closest in meaning to “Jubilant”.",
          "options": [
            "Angry",
            "Mournful",
            "Joyful",
            "Nervous"
          ],
          "correct": 2,
          "explanation": "Jubilant means extremely happy or joyful.",
          "source": "Individual PDF extraction: 2025-english-09-question-paper.pdf"
        },
        {
          "id": "101-2025-2025-english-09-question-paper-Q14",
          "type": "mcq",
          "level": "L2",
          "difficulty": "medium",
          "question": "Despite the chaos around him, the monk remained stoic, showing no signs of distress or excitement. What does ”stoic” mean in this context?",
          "options": [
            "Confused and irritated",
            "Emotionless and calm",
            "Extremely cheerful",
            "Outspoken and loud"
          ],
          "correct": 1,
          "explanation": "Stoic means calm and not showing emotion despite pain, distress, or excitement.",
          "source": "Individual PDF extraction: 2025-english-09-question-paper.pdf"
        },
        {
          "id": "101-2025-2025-english-09-question-paper-Q15",
          "type": "mcq",
          "level": "L2",
          "difficulty": "medium",
          "question": "The smell of old books often fills me with a sense of reminding me of my childhood days. Choose the word that best fits this feeling.",
          "options": [
            "regret",
            "joy",
            "nostalgia",
            "anxiety"
          ],
          "correct": 2,
          "explanation": "Nostalgia is a sentimental longing for the past, especially childhood or earlier experiences.",
          "source": "Individual PDF extraction: 2025-english-09-question-paper.pdf"
        },
        {
          "id": "101-2025-2025-english-09-question-paper-Q16",
          "type": "mcq",
          "level": "L2",
          "difficulty": "medium",
          "question": "Which of the following sentences uses the word ”Absturb” correctly?",
          "options": [
            "The explanation he gave was completely absturb.",
            "She absturb the offer politely.",
            "He absturb to the committee’s view.",
            "None of the above."
          ],
          "correct": null,
          "explanation": "Source PDF contains a spelling/wording error: the tested word appears as \"Absturb\", which is not a standard English word. This item should remain under source review rather than being used as a student-ready question.",
          "source": "Individual PDF extraction: 2025-english-09-question-paper.pdf"
        }
      ]
    }
  ]
}
